easydocxpy/EasyDocxPy.py
easydocxpy/__init__.py
easydocxpy-0.1.0.dist-info/METADATA
easydocxpy-0.1.0.dist-info/WHEEL
easydocxpy-0.1.0.dist-info/RECORD
