Metadata-Version: 2.1
Name: easydocxpy
Version: 0.1.0
Summary: Librería para simplificar el uso de python-docx
License: MIT
Author: CristianTacoronteRivero
Author-email: tacoronteriverocristian@gmail.com
Requires-Python: >=3.10,<4.0
Classifier: License :: OSI Approved :: MIT License
Classifier: Programming Language :: Python :: 3
Classifier: Programming Language :: Python :: 3.10
Classifier: Programming Language :: Python :: 3.11
Requires-Dist: pandas (>=2.2.0,<3.0.0)
Requires-Dist: python-docx (>=1.1.0,<2.0.0)
